mask/__init__.py
mask/_common.py
mask/helper.py
mask/mask.py
the_mask-0.0.1.dist-info/LICENSE
the_mask-0.0.1.dist-info/METADATA
the_mask-0.0.1.dist-info/WHEEL
the_mask-0.0.1.dist-info/top_level.txt
the_mask-0.0.1.dist-info/RECORD
