Metadata-Version: 2.1
Name: the-mask
Version: 0.0.1
Summary: A package to hide/mask PII information in the JSON object
Author-email: Parvathirajan Natarajan <parvathi_rajan@hotmail.com>
License: MIT
Project-URL: Homepage, https://github.com/parvathirajan/the-mask
Project-URL: Bug Tracker, https://github.com/parvathirajan/the-mask/issues
Project-URL: Source Code, https://github.com/parvathirajan/the-mask
Keywords: masking,PII,data-security
Classifier: Development Status :: 5 - Production/Stable
Classifier: Environment :: Console
Classifier: Intended Audience :: Developers
Classifier: License :: OSI Approved :: MIT License
Classifier: Operating System :: OS Independent
Classifier: Programming Language :: Python
Classifier: Programming Language :: Python :: 3 :: Only
Classifier: Programming Language :: Python :: 3.7
Classifier: Programming Language :: Python :: 3.8
Classifier: Programming Language :: Python :: 3.9
Classifier: Programming Language :: Python :: 3.10
Classifier: Programming Language :: Python :: 3.11
Classifier: Topic :: Software Development :: Libraries :: Python Modules
Classifier: Topic :: Scientific/Engineering
Requires-Python: >=3.6
License-File: LICENSE
